{"pranala": "https://kbbi.kemdikbud.go.id/entri/mah", "entri": [{"nama": "mah", "nomor": "1", "kata_dasar": [], "pelafalan": "", "bentuk_tidak_baku": [], "varian": [], "makna": [{"kelas": [{"kode": "a", "nama": "Adjektiva", "deskripsi": "kata yang menjelaskan nomina atau pronomina"}], "submakna": ["maha (misalnya mahraja, maharaja)"], "info": "", "contoh": []}]}, {"nama": "mah", "nomor": "2", "kata_dasar": [], "pelafalan": "", "bentuk_tidak_baku": [], "varian": [], "makna": [{"kelas": [{"kode": "p", "nama": "Partikel", "deskripsi": "kelas kata yang meliputi kata depan, kata sambung, kata seru, kata sandang, ucapan salam"}, {"kode": "cak", "nama": "Cakapan", "deskripsi": "menandai kata yang digunakan dalam ragam takbaku"}, {"kode": "Sd", "nama": "Sunda", "deskripsi": "-"}], "submakna": ["kata untuk menyatakan penegasan ucapan, biasanya digunakan setelah kata ganti orang", "sih"], "info": "", "contoh": ["dia -- jarang di rumah"]}]}]}