{"pranala": "https://kbbi.kemdikbud.go.id/entri/majalah", "entri": [{"nama": "ma.ja.lah", "nomor": "", "kata_dasar": [], "pelafalan": "", "bentuk_tidak_baku": [], "varian": [], "makna": [{"kelas": [{"kode": "n", "nama": "Nomina", "deskripsi": "kata benda"}], "submakna": ["terbitan berkala yang isinya meliputi berbagai liputan jurnalistik dan pandangan tentang topik aktual yang patut diketahui pembaca, menurut waktu penerbitannya dibedakan atas majalah bulanan, tengah bulanan, mingguan, dan sebagainya, menurut pengkhususan isinya dibedakan atas majalah berita, wanita, remaja, olahraga, sastra, ilmu pengetahuan tertentu, dan sebagainya"], "info": "", "contoh": []}]}]}