{"pranala": "https://kbbi.kemdikbud.go.id/entri/makhraj", "entri": [{"nama": "makh.raj", "nomor": "", "kata_dasar": [], "pelafalan": "", "bentuk_tidak_baku": ["mahraj"], "varian": [], "makna": [{"kelas": [{"kode": "n", "nama": "Nomina", "deskripsi": "kata benda"}, {"kode": "Ar", "nama": "Arab", "deskripsi": "-"}], "submakna": ["daerah artikulasi"], "info": "", "contoh": []}, {"kelas": [{"kode": "n", "nama": "Nomina", "deskripsi": "kata benda"}, {"kode": "Ar", "nama": "Arab", "deskripsi": "-"}], "submakna": ["ketepatan ucapan"], "info": "", "contoh": []}]}]}