{"pranala": "https://kbbi.kemdikbud.go.id/entri/mambu", "entri": [{"nama": "mam.bu", "nomor": "", "kata_dasar": [], "pelafalan": "", "bentuk_tidak_baku": [], "varian": [], "makna": [{"kelas": [{"kode": "a", "nama": "Adjektiva", "deskripsi": "kata yang menjelaskan nomina atau pronomina"}, {"kode": "Jw", "nama": "Jawa", "deskripsi": "-"}], "submakna": ["berbau"], "info": "", "contoh": []}, {"kelas": [{"kode": "a", "nama": "Adjektiva", "deskripsi": "kata yang menjelaskan nomina atau pronomina"}, {"kode": "Jw", "nama": "Jawa", "deskripsi": "-"}], "submakna": ["basi (tentang makanan)"], "info": "", "contoh": []}]}]}