{"pranala": "https://kbbi.kemdikbud.go.id/entri/masase", "entri": [{"nama": "ma.sa.se", "nomor": "", "kata_dasar": [], "pelafalan": "/masas\u00ea/", "bentuk_tidak_baku": [], "varian": [], "makna": [{"kelas": [{"kode": "n", "nama": "Nomina", "deskripsi": "kata benda"}], "submakna": ["pemijatan, pengurutan, dan sebagainya pada bagian badan tertentu dengan tangan atau alat-alat khusus untuk melancarkan peredaran darah sebagai cara pengobatan atau untuk menghilangkan rasa capai"], "info": "", "contoh": []}]}]}