{"pranala": "https://kbbi.kemdikbud.go.id/entri/memagari", "entri": [{"nama": "me.ma.gari", "nomor": "", "kata_dasar": ["pagar"], "pelafalan": "", "bentuk_tidak_baku": ["mempagari"], "varian": [], "makna": [{"kelas": [{"kode": "v", "nama": "Verba", "deskripsi": "kata kerja"}], "submakna": ["memasangi pagar"], "info": "", "contoh": ["ia ~ pekarangannya dengan bambu"]}, {"kelas": [{"kode": "v", "nama": "Verba", "deskripsi": "kata kerja"}, {"kode": "ki", "nama": "kiasan", "deskripsi": ""}], "submakna": ["melindungi (supaya jangan diganggu, diserang, dan sebagainya)"], "info": "", "contoh": ["pasukan keamanan ~ tamu agung"]}, {"kelas": [{"kode": "v", "nama": "Verba", "deskripsi": "kata kerja"}, {"kode": "Isl", "nama": "Agama Islam", "deskripsi": "-"}], "submakna": ["memberi panjar", "memberi uang muka"], "info": "", "contoh": ["untuk ~ rumah, bacalah Do'a Nur Nubuwwah satu kali"]}]}]}