{"pranala": "https://kbbi.kemdikbud.go.id/entri/memadui", "entri": [{"nama": "me.ma.dui", "nomor": "", "kata_dasar": ["madu (2)"], "pelafalan": "", "bentuk_tidak_baku": [], "varian": [], "makna": [{"kelas": [{"kode": "v", "nama": "Verba", "deskripsi": "kata kerja"}], "submakna": ["menjadi madu terhadap"], "info": "", "contoh": ["kalau kamu mau diperistri suami saudara sepupumu berarti kamu hendak ~ saudara sepupumu sendiri"]}, {"kelas": [{"kode": "v", "nama": "Verba", "deskripsi": "kata kerja"}], "submakna": ["memberi madu (kepada istri)"], "info": "", "contoh": ["tega nian kau ~ istrimu yang sebaik itu"]}]}]}