{"pranala": "http://kbbi.kemdikbud.go.id/entri/memihakkan", "entri": [{"nama": "me.mi.hak.kan", "nomor": "", "kata_dasar": ["pihak"], "pelafalan": "", "bentuk_tidak_baku": [], "varian": [], "makna": [{"kelas": [{"kode": "v", "nama": "Verba", "deskripsi": "kata kerja"}], "submakna": ["menceraikan (memisahkan) menjadi beberapa pihak"], "info": "", "contoh": []}, {"kelas": [{"kode": "v", "nama": "Verba", "deskripsi": "kata kerja"}], "submakna": ["menyisikan", "mengesampingkan"], "info": "", "contoh": []}, {"kelas": [{"kode": "v", "nama": "Verba", "deskripsi": "kata kerja"}], "submakna": ["memasukkan ke dalam salah satu pihak"], "info": "", "contoh": []}]}]}