{"pranala": "http://kbbi.kemdikbud.go.id/entri/mendekatkan", "entri": [{"nama": "men.de.kat.kan", "nomor": "", "kata_dasar": ["dekat"], "pelafalan": "", "bentuk_tidak_baku": [], "varian": [], "makna": [{"kelas": [{"kode": "v", "nama": "Verba", "deskripsi": "kata kerja"}], "submakna": ["menjadikan dekat (berdekatan)", "membawa (menggeser, menarik, dan sebagainya) supaya berhampiran (berdekatan)", "mendampingkan"], "info": "", "contoh": ["anak itu ~ mulutnya ke telinga ibunya untuk membisikkan sesuatu"]}]}]}