{"pranala": "http://kbbi.kemdikbud.go.id/entri/mendemiliterisasi", "entri": [{"nama": "men.de.mi.li.te.ri.sa.si", "nomor": "", "kata_dasar": ["demiliterisasi"], "pelafalan": "", "bentuk_tidak_baku": [], "varian": [], "makna": [{"kelas": [{"kode": "v", "nama": "Verba", "deskripsi": "kata kerja"}], "submakna": ["membebaskan (melepaskan) dari ikatan atau dari sifat-sifat kemiliteran"], "info": "", "contoh": []}, {"kelas": [{"kode": "v", "nama": "Verba", "deskripsi": "kata kerja"}], "submakna": ["membebaskan (suatu daerah) dari kekuasaan atau pendudukan militer"], "info": "", "contoh": []}]}]}