{"pranala": "http://kbbi.kemdikbud.go.id/entri/menengkel", "entri": [{"nama": "me.neng.kel", "nomor": "", "kata_dasar": ["tengkel"], "pelafalan": "", "bentuk_tidak_baku": [], "varian": [], "makna": [{"kelas": [{"kode": "v", "nama": "Verba", "deskripsi": "kata kerja"}], "submakna": ["menjadi butir-butir", "membutir"], "info": "", "contoh": ["bahan obat itu setelah diolah dengan mesin, akhirnya ~ dengan sendirinya"]}, {"kelas": [{"kode": "v", "nama": "Verba", "deskripsi": "kata kerja"}], "submakna": ["melekat", "berlekat-lekat"], "info": "", "contoh": ["manisan cermai itu ~"]}]}]}