{"pranala": "https://kbbi.kemdikbud.go.id/entri/mengeblok", "entri": [{"nama": "me.nge.blok", "nomor": "", "kata_dasar": ["blok"], "pelafalan": "", "bentuk_tidak_baku": [], "varian": [], "makna": [{"kelas": [{"kode": "v", "nama": "Verba", "deskripsi": "kata kerja"}], "submakna": ["melakukan blok"], "info": "", "contoh": []}, {"kelas": [{"kode": "v", "nama": "Verba", "deskripsi": "kata kerja"}], "submakna": ["memilih bagian dokumen tertentu (teks, gambar, dan sebagainya) untuk mengaplikasikan perintah pada bagian tersebut, misalnya menyalin, memindahkan, atau menghapus (tentang komputer)"], "info": "", "contoh": []}]}]}