{"pranala": "https://kbbi.kemdikbud.go.id/entri/mengawali", "entri": [{"nama": "me.nga.wali", "nomor": "", "kata_dasar": ["kawal"], "pelafalan": "", "bentuk_tidak_baku": [], "varian": [], "makna": [{"kelas": [{"kode": "v", "nama": "Verba", "deskripsi": "kata kerja"}], "submakna": ["mengawasi", "mengontrol"], "info": "", "contoh": []}]}, {"nama": "meng.a.wali", "nomor": "", "kata_dasar": ["awal"], "pelafalan": "", "bentuk_tidak_baku": [], "varian": [], "makna": [{"kelas": [{"kode": "v", "nama": "Verba", "deskripsi": "kata kerja"}], "submakna": ["memulai", "mendahului"], "info": "", "contoh": ["nyanyian bersama ~ api unggun itu"]}]}]}