{"pranala": "https://kbbi.kemdikbud.go.id/entri/mengamban", "entri": [{"nama": "me.ngam.ban", "nomor": "", "kata_dasar": ["kamban (1)"], "pelafalan": "", "bentuk_tidak_baku": [], "varian": [], "makna": [{"kelas": [{"kode": "v", "nama": "Verba", "deskripsi": "kata kerja"}], "submakna": ["mengikat"], "info": "", "contoh": ["ia ~ beban itu di atas pelana kudanya"]}]}, {"nama": "me.ngam.ban", "nomor": "", "kata_dasar": ["kamban (2)"], "pelafalan": "", "bentuk_tidak_baku": [], "varian": [], "makna": [{"kelas": [{"kode": "v", "nama": "Verba", "deskripsi": "kata kerja"}], "submakna": ["memeluk dari belakang"], "info": "", "contoh": []}]}]}