{"pranala": "http://kbbi.kemdikbud.go.id/entri/mengguncangkan", "entri": [{"nama": "meng.gun.cang.kan", "nomor": "", "kata_dasar": ["guncang"], "pelafalan": "", "bentuk_tidak_baku": [], "varian": [], "makna": [{"kelas": [{"kode": "v", "nama": "Verba", "deskripsi": "kata kerja"}], "submakna": ["menggoyangkan kuat-kuat", "menggerak-gerakkan hingga berguncang"], "info": "", "contoh": []}, {"kelas": [{"kode": "v", "nama": "Verba", "deskripsi": "kata kerja"}, {"kode": "ki", "nama": "kiasan", "deskripsi": ""}], "submakna": ["menyebabkan tidak tetap (tidak tenang, tidak aman, dan sebagainya)"], "info": "", "contoh": ["tindakan itu akan ~ harga minyak di luar negeri"]}]}]}