{"pranala": "http://kbbi.kemdikbud.go.id/entri/menjumlah", "entri": [{"nama": "men.jum.lah", "nomor": "", "kata_dasar": ["jumlah"], "pelafalan": "", "bentuk_tidak_baku": [], "varian": [], "makna": [{"kelas": [{"kode": "v", "nama": "Verba", "deskripsi": "kata kerja"}], "submakna": ["menghitung (berapa banyaknya)"], "info": "", "contoh": ["ia sedang ~ uang sumbangan yang masuk"]}, {"kelas": [{"kode": "v", "nama": "Verba", "deskripsi": "kata kerja"}], "submakna": ["menambah (dalam berhitung atau matematika)"], "info": "", "contoh": ["ia belajar ~ dan mengurangi"]}]}]}