{"pranala": "https://kbbi.kemdikbud.go.id/entri/menyuap", "entri": [{"nama": "me.nyu.ap", "nomor": "", "kata_dasar": ["suap"], "pelafalan": "", "bentuk_tidak_baku": [], "varian": [], "makna": [{"kelas": [{"kode": "v", "nama": "Verba", "deskripsi": "kata kerja"}], "submakna": ["makan dengan tangan (tidak dengan sendok dan sebagainya)"], "info": "", "contoh": []}, {"kelas": [{"kode": "v", "nama": "Verba", "deskripsi": "kata kerja"}], "submakna": ["memberi makan dengan memasukkan makanan ke dalam mulut yang disuapi"], "info": "", "contoh": ["~ anak"]}, {"kelas": [{"kode": "v", "nama": "Verba", "deskripsi": "kata kerja"}, {"kode": "ki", "nama": "kiasan", "deskripsi": ""}], "submakna": ["memberi uang sogok", "menyogok", "menyuapi"], "info": "", "contoh": ["sebenarnya uang sebanyak itu disediakan untuk ~ orang-orang yang berpengaruh"]}]}]}