{"pranala": "https://kbbi.kemdikbud.go.id/entri/meresek-resek", "entri": [{"nama": "me.re.sek-re.sek", "nomor": "", "kata_dasar": ["resek (2)"], "pelafalan": "", "bentuk_tidak_baku": [], "varian": [], "makna": [{"kelas": [{"kode": "v", "nama": "Verba", "deskripsi": "kata kerja"}], "submakna": ["mencari dengan meraba-raba"], "info": "", "contoh": ["dalam gelap itu kedua orang itu pun ~ tempat tidur masing-masing"]}, {"kelas": [{"kode": "v", "nama": "Verba", "deskripsi": "kata kerja"}], "submakna": ["mencari keterangan", "mengusut", "menyelidiki"], "info": "", "contoh": ["polisi ~ penduduk kampung yang dicurigai"]}]}]}