{"pranala": "http://kbbi.kemdikbud.go.id/entri/balot", "entri": [{"nama": "ba.lot", "nomor": "", "kata_dasar": [], "pelafalan": "", "bentuk_tidak_baku": [], "varian": [], "makna": [{"kelas": [{"kode": "n", "nama": "Nomina", "deskripsi": "kata benda"}, {"kode": "Pol", "nama": "Politik dan Pemerintahan", "deskripsi": "-"}], "submakna": ["suara yang diberikan dalam pemilihan"], "info": "", "contoh": []}, {"kelas": [{"kode": "n", "nama": "Nomina", "deskripsi": "kata benda"}, {"kode": "Pol", "nama": "Politik dan Pemerintahan", "deskripsi": "-"}], "submakna": ["kertas yang memuat nama calon untuk dipilih yang dibagi-bagikan kepada para pemilih agar mereka dapat menentukan pilihannya atau menambahkan nama yang belum dicantumkan"], "info": "", "contoh": []}]}]}