{"pranala": "http://kbbi.kemdikbud.go.id/entri/bedaya", "entri": [{"nama": "be.da.ya", "nomor": "", "kata_dasar": [], "pelafalan": "/b\u00eadaya/", "bentuk_tidak_baku": [], "varian": [], "makna": [{"kelas": [{"kode": "n", "nama": "Nomina", "deskripsi": "kata benda"}], "submakna": ["penari wanita istana", "serimpi"], "info": "", "contoh": ["waktu itu ia bertugas menjadi --"]}, {"kelas": [{"kode": "n", "nama": "Nomina", "deskripsi": "kata benda"}], "submakna": ["tari bedaya"], "info": "", "contoh": []}]}]}