{"pranala": "https://kbbi.kemdikbud.go.id/entri/bercekikikan", "entri": [{"nama": "ber.ce.ki.kik.an", "nomor": "", "kata_dasar": ["cekikik"], "pelafalan": "", "bentuk_tidak_baku": [], "varian": [], "makna": [{"kelas": [{"kode": "v", "nama": "Verba", "deskripsi": "kata kerja"}], "submakna": ["mengeluarkan bunyi \u201ckik, kik\u201d karena tertawa-tawa kecil agak tertahan-tahan"], "info": "", "contoh": []}, {"kelas": [{"kode": "v", "nama": "Verba", "deskripsi": "kata kerja"}], "submakna": ["tertawa-tawa kecil agak tertahan-tahan"], "info": "", "contoh": []}]}]}