{"pranala": "http://kbbi.kemdikbud.go.id/entri/berguru", "entri": [{"nama": "ber.gu.ru", "nomor": "", "kata_dasar": ["guru"], "pelafalan": "", "bentuk_tidak_baku": [], "varian": [], "makna": [{"kelas": [{"kode": "v", "nama": "Verba", "deskripsi": "kata kerja"}], "submakna": ["belajar"], "info": "", "contoh": ["kepadanyalah ia banyak ~"]}, {"kelas": [{"kode": "v", "nama": "Verba", "deskripsi": "kata kerja"}], "submakna": ["berlaku sebagai guru"], "info": "", "contoh": ["sebenarnya ia bukan guru, melainkan pandai ~"]}]}]}