{"pranala": "http://kbbi.kemdikbud.go.id/entri/bermusuh", "entri": [{"nama": "ber.mu.suh", "nomor": "", "kata_dasar": ["musuh"], "pelafalan": "", "bentuk_tidak_baku": [], "varian": [], "makna": [{"kelas": [{"kode": "v", "nama": "Verba", "deskripsi": "kata kerja"}], "submakna": ["musuh-memusuhi", "berlawanan (berlaku seperti musuh dengan musuh)"], "info": "", "contoh": ["kedua pihak selalu ~", "mendamaikan kedua suku yang ~"]}, {"kelas": [{"kode": "v", "nama": "Verba", "deskripsi": "kata kerja"}], "submakna": ["saling memusuhi"], "info": "", "contoh": []}]}]}