{"pranala": "https://kbbi.kemdikbud.go.id/entri/buar", "entri": [{"nama": "bu.ar", "nomor": "", "kata_dasar": [], "pelafalan": "", "bentuk_tidak_baku": [], "varian": [], "makna": [{"kelas": [{"kode": "a", "nama": "Adjektiva", "deskripsi": "kata yang menjelaskan nomina atau pronomina"}, {"kode": "ark", "nama": "Arkais", "deskripsi": "menandai kata yang tidak lazim"}], "submakna": ["suka menghamburkan uang", "boros", "royal"], "info": "", "contoh": ["meskipun banyak pencahariannya, ia tidak dapat kaya karena ia --"]}]}]}