{"pranala": "https://kbbi.kemdikbud.go.id/entri/buku%20biru", "entri": [{"nama": "buku biru", "nomor": "", "kata_dasar": ["buku (1)"], "pelafalan": "", "bentuk_tidak_baku": [], "varian": [], "makna": [{"kelas": [], "submakna": ["buku yang memuat nama-nama orang terkemuka"], "info": "", "contoh": []}, {"kelas": [], "submakna": ["buku yang memuat saran, pertimbangan, dan usulan tentang suatu masalah"], "info": "", "contoh": ["laporan berbentuk -- biru itu menyatakan bahwa roket pelambung harus diuji coba dalam kedudukan horizontal"]}, {"kelas": [], "submakna": ["buku laporan pemerintah"], "info": "", "contoh": []}]}]}