{"pranala": "https://kbbi.kemdikbud.go.id/entri/ajun%20komisaris%20polisi", "entri": [{"nama": "ajun komisaris polisi", "nomor": "", "kata_dasar": ["ajun (2)"], "pelafalan": "", "bentuk_tidak_baku": [], "varian": [], "makna": [{"kelas": [], "submakna": ["pangkat perwira pertama peringkat pertama dalam kepolisian, satu tingkat di bawah komisaris polisi dan satu tingkat di atas ajun inspektur polisi satu (tanda pangkatnya tiga balok emas yang ditempatkan di bahu baju)"], "info": "", "contoh": []}]}]}