{"pranala": "https://kbbi.kemdikbud.go.id/entri/analog", "entri": [{"nama": "ana.log", "nomor": "", "kata_dasar": [], "pelafalan": "", "bentuk_tidak_baku": [], "varian": [], "makna": [{"kelas": [{"kode": "a", "nama": "Adjektiva", "deskripsi": "kata yang menjelaskan nomina atau pronomina"}], "submakna": ["bersangkutan dengan analogi", "sama", "serupa"], "info": "", "contoh": ["masalah suku terasing di Indonesia -- dengan masalah suku terasing di Filipina dan Hawaii"]}, {"kelas": [{"kode": "a", "nama": "Adjektiva", "deskripsi": "kata yang menjelaskan nomina atau pronomina"}, {"kode": "Komp", "nama": "Komputer", "deskripsi": "-"}], "submakna": ["bersangkut paut atau berhubungan dengan sistem atau peranti komputer yang menyajikan data yang bermacam-macam berdasarkan kualitas fisik yang terukur"], "info": "", "contoh": []}, {"kelas": [{"kode": "n", "nama": "Nomina", "deskripsi": "kata benda"}], "submakna": ["bahan kimia dengan struktur yang mirip dengan yang lain, tp berbeda sedikit dalam komposisi"], "info": "", "contoh": []}]}]}