{"pranala": "https://kbbi.kemdikbud.go.id/entri/anatomi", "entri": [{"nama": "ana.to.mi", "nomor": "", "kata_dasar": [], "pelafalan": "", "bentuk_tidak_baku": [], "varian": [], "makna": [{"kelas": [{"kode": "n", "nama": "Nomina", "deskripsi": "kata benda"}], "submakna": ["ilmu yang melukiskan letak dan hubungan bagian-bagian tubuh manusia, binatang, atau tumbuh-tumbuhan", "ilmu tasrih", "ilmu urai"], "info": "", "contoh": []}, {"kelas": [{"kode": "n", "nama": "Nomina", "deskripsi": "kata benda"}], "submakna": ["uraian yang mendalam tentang sesuatu"], "info": "", "contoh": ["-- revolusi"]}]}]}