{"pranala": "http://kbbi.kemdikbud.go.id/entri/antipode", "entri": [{"nama": "an.ti.po.de", "nomor": "", "kata_dasar": [], "pelafalan": "/antipod\u00ea/", "bentuk_tidak_baku": [], "varian": [], "makna": [{"kelas": [{"kode": "n", "nama": "Nomina", "deskripsi": "kata benda"}], "submakna": ["dua tempat yang terletak di belahan bumi yang berlawanan"], "info": "", "contoh": []}, {"kelas": [{"kode": "n", "nama": "Nomina", "deskripsi": "kata benda"}], "submakna": ["belahan bumi yang letaknya berlawanan dengan tempat kita"], "info": "", "contoh": []}, {"kelas": [{"kode": "n", "nama": "Nomina", "deskripsi": "kata benda"}, {"kode": "ki", "nama": "kiasan", "deskripsi": ""}], "submakna": ["orang-orang yang saling bertentangan atau berlawanan pendirian"], "info": "", "contoh": ["\u201cPujangga Baru\u201d bukan hanya Takdir, melainkan juga --nya Sanusi Pane"]}]}]}