{"pranala": "http://kbbi.kemdikbud.go.id/entri/imbas", "entri": [{"nama": "im.bas", "nomor": "", "kata_dasar": [], "pelafalan": "", "bentuk_tidak_baku": [], "varian": [], "makna": [{"kelas": [{"kode": "n", "nama": "Nomina", "deskripsi": "kata benda"}], "submakna": ["gerakan atau aliran udara (ditimbulkan oleh gerakan kipas, benda bergerak, dan sebagainya)"], "info": "", "contoh": []}, {"kelas": [{"kode": "n", "nama": "Nomina", "deskripsi": "kata benda"}], "submakna": ["dorongan", "akibat (tanpa disengaja terjadinya)"], "info": "", "contoh": []}, {"kelas": [{"kode": "n", "nama": "Nomina", "deskripsi": "kata benda"}], "submakna": ["penyakit yang disebabkan oleh hantu yang lewat dan sebagainya"], "info": "", "contoh": ["kata orang tua-tua, pada waktu magrib janganlah keluar rumah karena dapat terkena -- hantu"]}, {"kelas": [{"kode": "n", "nama": "Nomina", "deskripsi": "kata benda"}, {"kode": "Fis", "nama": "Fisika", "deskripsi": "-"}], "submakna": ["perolehan sesuatu sebagai akibat pengaruh sesuatu yang lain, misalnya imbas elektrostatik adalah pemberian muatan listrik statik pada sebuah benda dengan cara mendekatkan benda itu (tetapi tidak menyentuh) kepada sebuah benda yang sudah bermuatan listrik statik"], "info": "", "contoh": []}]}]}