{"pranala": "https://kbbi.kemdikbud.go.id/entri/interupsi", "entri": [{"nama": "in.te.rup.si", "nomor": "", "kata_dasar": [], "pelafalan": "/int\u00earupsi/", "bentuk_tidak_baku": [], "varian": [], "makna": [{"kelas": [{"kode": "n", "nama": "Nomina", "deskripsi": "kata benda"}], "submakna": ["penyelaan atau pemotongan (pembicaraan,pidato, dan sebagainya)"], "info": "", "contoh": []}, {"kelas": [{"kode": "n", "nama": "Nomina", "deskripsi": "kata benda"}, {"kode": "Komp", "nama": "Komputer", "deskripsi": "-"}], "submakna": ["sinyal suatu peranti ke prosesor komputer untuk meminta perhatian dari prosesor sebagai tanggapan terhadap galat program atau permintaan untuk layanan sistem operasi"], "info": "", "contoh": []}]}]}