{"pranala": "https://kbbi.kemdikbud.go.id/entri/interogasi", "entri": [{"nama": "in.te.ro.ga.si", "nomor": "", "kata_dasar": [], "pelafalan": "/int\u00earogasi/", "bentuk_tidak_baku": [], "varian": [], "makna": [{"kelas": [{"kode": "n", "nama": "Nomina", "deskripsi": "kata benda"}], "submakna": ["pertanyaan"], "info": "", "contoh": []}, {"kelas": [{"kode": "n", "nama": "Nomina", "deskripsi": "kata benda"}], "submakna": ["pemeriksaan terhadap seseorang melalui pertanyaan lisan yang bersistem"], "info": "", "contoh": []}]}]}