{"pranala": "https://kbbi.kemdikbud.go.id/entri/iwak%20basamu", "entri": [{"nama": "iwak ba.sa.mu", "nomor": "", "kata_dasar": [], "pelafalan": "", "bentuk_tidak_baku": [], "varian": [], "makna": [{"kelas": [{"kode": "n", "nama": "Nomina", "deskripsi": "kata benda"}, {"kode": "Tbg", "nama": "Tata Boga", "deskripsi": "-"}], "submakna": ["masakan khas Kalimantan berbahan ikan gabus, papuyu, dan lain-lain yang diasinkan selama berbulan-bulan dan diberi samu atau tumbukan beras yang disangrai"], "info": "", "contoh": []}]}]}