{"pranala": "https://kbbi.kemdikbud.go.id/entri/pelaga", "entri": [{"nama": "pe.la.ga", "nomor": "", "kata_dasar": ["laga"], "pelafalan": "", "bentuk_tidak_baku": [], "varian": [], "makna": [{"kelas": [{"kode": "n", "nama": "Nomina", "deskripsi": "kata benda"}], "submakna": ["ayam sabungan"], "info": "", "contoh": []}, {"kelas": [{"kode": "n", "nama": "Nomina", "deskripsi": "kata benda"}], "submakna": ["orang yang suka berlaga (berkelahi)"], "info": "", "contoh": []}]}, {"nama": "pe.la.ga", "nomor": "", "kata_dasar": [], "pelafalan": "/p\u00ealaga/", "bentuk_tidak_baku": [], "varian": [], "makna": [{"kelas": [], "submakna": ["\u2192 kapulaga"], "info": "", "contoh": []}]}]}