{"pranala": "https://kbbi.kemdikbud.go.id/entri/percetakan", "entri": [{"nama": "per.ce.tak.an", "nomor": "", "kata_dasar": ["cetak"], "pelafalan": "", "bentuk_tidak_baku": [], "varian": [], "makna": [{"kelas": [{"kode": "n", "nama": "Nomina", "deskripsi": "kata benda"}], "submakna": ["tempat (perusahaan) cetak-mencetak (buku dan sebagainya)", "kantor cetak"], "info": "", "contoh": ["buku-buku ini dicetak di ~ yang ada di kawasan industri"]}, {"kelas": [{"kode": "n", "nama": "Nomina", "deskripsi": "kata benda"}], "submakna": ["perihal cetak-mencetak", "segala sesuatu yang berhubungan dengan cetak-mencetak"], "info": "", "contoh": ["para pengusaha ~ tidak lepas dari norma dan kebiasaan itu"]}]}]}