{"pranala": "https://kbbi.kemdikbud.go.id/entri/pesero", "entri": [{"nama": "pe.se.ro", "nomor": "", "kata_dasar": ["sero (2)"], "pelafalan": "", "bentuk_tidak_baku": ["persero"], "varian": [], "makna": [{"kelas": [{"kode": "n", "nama": "Nomina", "deskripsi": "kata benda"}], "submakna": ["orang yang ikut menanamkan saham", "pemegang saham (peserta dalam perserikatan dagang)"], "info": "", "contoh": []}]}, {"nama": "pe.se.ro", "nomor": "", "kata_dasar": [], "pelafalan": "/p\u00eas\u00e9ro/", "bentuk_tidak_baku": ["persero"], "varian": [], "makna": [{"kelas": [], "submakna": ["\u2192 sero (2)"], "info": "", "contoh": []}]}]}