{"pranala": "https://kbbi.kemdikbud.go.id/entri/produk", "entri": [{"nama": "pro.duk", "nomor": "", "kata_dasar": [], "pelafalan": "", "bentuk_tidak_baku": [], "varian": [], "makna": [{"kelas": [{"kode": "n", "nama": "Nomina", "deskripsi": "kata benda"}], "submakna": ["barang atau jasa yang dibuat dan ditambah gunanya atau nilainya dalam proses produksi dan menjadi hasil akhir dari proses produksi itu"], "info": "", "contoh": []}, {"kelas": [{"kode": "n", "nama": "Nomina", "deskripsi": "kata benda"}], "submakna": ["benda atau yang bersifat kebendaan seperti barang, bahan, atau bangunan yang merupakan hasil konstruksi"], "info": "", "contoh": []}, {"kelas": [{"kode": "n", "nama": "Nomina", "deskripsi": "kata benda"}], "submakna": ["hasil", "hasil kerja"], "info": "", "contoh": []}, {"kelas": [{"kode": "n", "nama": "Nomina", "deskripsi": "kata benda"}, {"kode": "Mat", "nama": "Matematika", "deskripsi": "-"}], "submakna": ["hasil kali"], "info": "", "contoh": []}]}]}