{"pranala": "http://kbbi.kemdikbud.go.id/entri/yahadian", "entri": [{"nama": "Ya.ha.di.an", "nomor": "", "kata_dasar": [], "pelafalan": "", "bentuk_tidak_baku": [], "varian": [], "makna": [{"kelas": [{"kode": "n", "nama": "Nomina", "deskripsi": "kata benda"}], "submakna": ["suku bangsa yang mendiami wilayah Kabupaten Sorong, Provinsi Papua"], "info": "", "contoh": []}, {"kelas": [{"kode": "n", "nama": "Nomina", "deskripsi": "kata benda"}], "submakna": ["bahasa yang dituturkan suku Yahadian"], "info": "", "contoh": []}]}]}