{"pranala": "https://kbbi.kemdikbud.go.id/entri/segel", "entri": [{"nama": "se.gel", "nomor": "", "kata_dasar": [], "pelafalan": "/s\u00e8g\u00eal/", "bentuk_tidak_baku": [], "varian": [], "makna": [{"kelas": [{"kode": "n", "nama": "Nomina", "deskripsi": "kata benda"}], "submakna": ["tera", "cap", "meterai"], "info": "", "contoh": []}, {"kelas": [{"kode": "n", "nama": "Nomina", "deskripsi": "kata benda"}, {"kode": "ark", "nama": "Arkais", "deskripsi": "menandai kata yang tidak lazim"}], "submakna": ["surat kecil (untuk membeli barang-barang pembagian)"], "info": "", "contoh": []}]}]}