{"pranala": "https://kbbi.kemdikbud.go.id/entri/senantan", "entri": [{"nama": "se.nan.tan", "nomor": "", "kata_dasar": [], "pelafalan": "/s\u00eanantan/", "bentuk_tidak_baku": [], "varian": [], "makna": [{"kelas": [{"kode": "a", "nama": "Adjektiva", "deskripsi": "kata yang menjelaskan nomina atau pronomina"}, {"kode": "kl", "nama": "Klasik", "deskripsi": "menandai kata yang digunakan dalam kesusastraan Melayu Klasik"}], "submakna": ["putih seperti santan", "kinantan"], "info": "", "contoh": []}]}]}