{"pranala": "https://kbbi.kemdikbud.go.id/entri/sepeling", "entri": [{"nama": "se.pe.ling", "nomor": "", "kata_dasar": [], "pelafalan": "/s\u00eap\u00e8ling/", "bentuk_tidak_baku": [], "varian": [], "makna": [{"kelas": [{"kode": "n", "nama": "Nomina", "deskripsi": "kata benda"}, {"kode": "cak", "nama": "Cakapan", "deskripsi": "menandai kata yang digunakan dalam ragam takbaku"}], "submakna": ["sesuatu yang sengaja dilebihkan daripada yang diperlukan", "kelebihan"], "info": "", "contoh": []}, {"kelas": [{"kode": "n", "nama": "Nomina", "deskripsi": "kata benda"}, {"kode": "cak", "nama": "Cakapan", "deskripsi": "menandai kata yang digunakan dalam ragam takbaku"}], "submakna": ["loncer", "longgar (roda, setir, mobil, dan sebagainya)"], "info": "", "contoh": []}]}]}