{"pranala": "https://kbbi.kemdikbud.go.id/entri/serabut", "entri": [{"nama": "se.ra.but", "nomor": "", "kata_dasar": [], "pelafalan": "/s\u00earabut/", "bentuk_tidak_baku": [], "varian": [], "makna": [{"kelas": [{"kode": "n", "nama": "Nomina", "deskripsi": "kata benda"}], "submakna": ["serat-serat seperti pada sabut"], "info": "", "contoh": []}, {"kelas": [{"kode": "n", "nama": "Nomina", "deskripsi": "kata benda"}], "submakna": ["barang yang rupanya seperti bulu atau serat"], "info": "", "contoh": []}, {"kelas": [{"kode": "n", "nama": "Nomina", "deskripsi": "kata benda"}], "submakna": ["sabut halus"], "info": "", "contoh": []}, {"kelas": [{"kode": "n", "nama": "Nomina", "deskripsi": "kata benda"}], "submakna": ["struktur jaringan yang berbentuk panjang seperti benang"], "info": "", "contoh": []}]}]}