{"pranala": "http://kbbi.kemdikbud.go.id/entri/setimbang", "entri": [{"nama": "se.tim.bang", "nomor": "", "kata_dasar": ["timbang (1)"], "pelafalan": "", "bentuk_tidak_baku": [], "varian": [], "makna": [{"kelas": [{"kode": "a", "nama": "Adjektiva", "deskripsi": "kata yang menjelaskan nomina atau pronomina"}], "submakna": ["sama beratnya"], "info": "", "contoh": ["beban di depan harus ~ dengan beban di belakang"]}, {"kelas": [{"kode": "a", "nama": "Adjektiva", "deskripsi": "kata yang menjelaskan nomina atau pronomina"}], "submakna": ["sama kedudukannya", "setara (sederajat dan sebagainya)"], "info": "", "contoh": []}, {"kelas": [{"kode": "a", "nama": "Adjektiva", "deskripsi": "kata yang menjelaskan nomina atau pronomina"}], "submakna": ["seimbang", "setimpal", "sebanding", "sepadan"], "info": "", "contoh": ["ia diberi penghargaan yang ~ dengan jasanya"]}, {"kelas": [{"kode": "a", "nama": "Adjektiva", "deskripsi": "kata yang menjelaskan nomina atau pronomina"}], "submakna": ["mantap (tidak goyang, tidak berubah)", "stabil"], "info": "", "contoh": ["keadaan ekonomi dewasa ini tidak ~"]}]}]}