{"pranala": "https://kbbi.kemdikbud.go.id/entri/siamang", "entri": [{"nama": "si.a.mang", "nomor": "1", "kata_dasar": [], "pelafalan": "", "bentuk_tidak_baku": [], "varian": [], "makna": [{"kelas": [{"kode": "n", "nama": "Nomina", "deskripsi": "kata benda"}], "submakna": ["monyet besar berbulu hitam yang tidak berekor, jari-jari tangannya yang kedua dan ketiga dipertautkan oleh selaput seolah-olah menyatu, makanannya buah-buahan, pucuk daun, telur burung, dan binatang kecil-kecil"], "info": "\u3014Symphalangus syndactylus\u3015", "contoh": []}]}, {"nama": "si.a.mang", "nomor": "2", "kata_dasar": [], "pelafalan": "", "bentuk_tidak_baku": [], "varian": [], "makna": [{"kelas": [{"kode": "n", "nama": "Nomina", "deskripsi": "kata benda"}, {"kode": "ark", "nama": "Arkais", "deskripsi": "menandai kata yang tidak lazim"}], "submakna": ["tungsten"], "info": "", "contoh": []}]}]}