{"pranala": "https://kbbi.kemdikbud.go.id/entri/sisipan", "entri": [{"nama": "si.sip.an", "nomor": "", "kata_dasar": ["sisip (1)"], "pelafalan": "", "bentuk_tidak_baku": [], "varian": [], "makna": [{"kelas": [{"kode": "n", "nama": "Nomina", "deskripsi": "kata benda"}], "submakna": ["sesuatu yang disisipkan"], "info": "", "contoh": ["pada lapisan batu candi itu hanya ada satu dua saja batu ~"]}, {"kelas": [{"kode": "n", "nama": "Nomina", "deskripsi": "kata benda"}, {"kode": "Ling", "nama": "Linguistik", "deskripsi": "-"}], "submakna": ["imbuhan (-el-, -er-, -em-, dan sebagainya) yang disisipkan di dalam kata", "infiks"], "info": "", "contoh": []}, {"kelas": [{"kode": "n", "nama": "Nomina", "deskripsi": "kata benda"}, {"kode": "Man", "nama": "Manajemen", "deskripsi": "-"}], "submakna": ["lembaran promosi yang disisipkan dalam majalah atau surat kabar"], "info": "", "contoh": []}, {"kelas": [{"kode": "n", "nama": "Nomina", "deskripsi": "kata benda"}, {"kode": "Kom", "nama": "Ilmu Komunikasi", "deskripsi": "-"}], "submakna": ["usaha menyisipkan siaran dalam bentuk gambar atau adegan pada siaran utama"], "info": "", "contoh": []}]}]}