{"pranala": "https://kbbi.kemdikbud.go.id/entri/sms", "entri": [{"nama": "SMS", "nomor": "", "kata_dasar": [], "pelafalan": "", "bentuk_tidak_baku": [], "varian": [], "makna": [{"kelas": [{"kode": "n", "nama": "Nomina", "deskripsi": "kata benda"}, {"kode": "sing", "nama": "singkatan", "deskripsi": ""}], "submakna": ["layanan pesan singkat", "short message service"], "info": "", "contoh": []}, {"kelas": [{"kode": "n", "nama": "Nomina", "deskripsi": "kata benda"}, {"kode": "Mil", "nama": "Kemiliteran", "deskripsi": "-"}, {"kode": "sing", "nama": "singkatan", "deskripsi": ""}], "submakna": ["senapan mesin sedang"], "info": "", "contoh": []}]}]}