{"pranala": "https://kbbi.kemdikbud.go.id/entri/stimulan", "entri": [{"nama": "sti.mu.lan", "nomor": "", "kata_dasar": [], "pelafalan": "", "bentuk_tidak_baku": [], "varian": [], "makna": [{"kelas": [{"kode": "n", "nama": "Nomina", "deskripsi": "kata benda"}], "submakna": ["sesuatu yang menjadi cambuk bagi peningkatan prestasi atau semangat bekerja (belajar dan sebagainya)", "pendorong", "penggiat", "perangsang"], "info": "", "contoh": ["ketidaklulusannya dalam ujian masuk universitas negeri merupakan -- baginya untuk maju dan belajar lebih giat lagi"]}]}]}