{"pranala": "https://kbbi.kemdikbud.go.id/entri/sub%E1%B8%A5%C4%81nahu%20wa%20ta%E2%80%99%C4%81la", "entri": [{"nama": "sub\u1e25\u0101nahu wa ta\u2019\u0101la", "nomor": "", "kata_dasar": [], "pelafalan": "", "bentuk_tidak_baku": [], "varian": [], "makna": [{"kelas": [{"kode": "ukp", "nama": "Ungkapan", "deskripsi": ""}, {"kode": "Ar", "nama": "Arab", "deskripsi": "-"}], "submakna": ["Mahasuci dan Mahatinggi Allah (biasanya dinyatakan sesudah menyebut nama Allah)", "disingkat Swt."], "info": "", "contoh": []}]}]}