{"pranala": "https://kbbi.kemdikbud.go.id/entri/varikosel", "entri": [{"nama": "va.ri.ko.sel", "nomor": "", "kata_dasar": [], "pelafalan": "/varikos\u00eal/", "bentuk_tidak_baku": [], "varian": [], "makna": [{"kelas": [{"kode": "n", "nama": "Nomina", "deskripsi": "kata benda"}, {"kode": "Dok", "nama": "Kedokteran dan Fisiologi", "deskripsi": "-"}], "submakna": ["pelebaran pembuluh darah balik (vena) pada kantung zakar karena adanya kelainan katup yang menghambat aliran darah"], "info": "", "contoh": []}]}]}