{"pranala": "https://kbbi.kemdikbud.go.id/entri/tabak", "entri": [{"nama": "ta.bak", "nomor": "1", "kata_dasar": [], "pelafalan": "", "bentuk_tidak_baku": [], "varian": [], "makna": [{"kelas": [{"kode": "n", "nama": "Nomina", "deskripsi": "kata benda"}], "submakna": ["talam besar tempat menghidangkan makanan"], "info": "", "contoh": []}]}, {"nama": "ta.bak", "nomor": "2", "kata_dasar": [], "pelafalan": "", "bentuk_tidak_baku": [], "varian": [], "makna": [{"kelas": [{"kode": "prakategorial", "nama": "prakategorial", "deskripsi": "kata tidak dipakai dalam bentuk dasarnya"}], "submakna": ["cari: menabak"], "info": "", "contoh": []}]}, {"nama": "ta.bak", "nomor": "3", "kata_dasar": [], "pelafalan": "", "bentuk_tidak_baku": [], "varian": [], "makna": [{"kelas": [{"kode": "n", "nama": "Nomina", "deskripsi": "kata benda"}], "submakna": ["kuali (belanga) tempat memasak nasi"], "info": "", "contoh": []}]}]}