{"pranala": "https://kbbi.kemdikbud.go.id/entri/takwin", "entri": [{"nama": "tak.win", "nomor": "", "kata_dasar": [], "pelafalan": "", "bentuk_tidak_baku": [], "varian": [], "makna": [{"kelas": [{"kode": "v", "nama": "Verba", "deskripsi": "kata kerja"}, {"kode": "Ar", "nama": "Arab", "deskripsi": "-"}], "submakna": ["menjadikan", "membentuk"], "info": "", "contoh": []}, {"kelas": [{"kode": "n", "nama": "Nomina", "deskripsi": "kata benda"}, {"kode": "Ar", "nama": "Arab", "deskripsi": "-"}], "submakna": ["uraian untuk menerangkan", "penjelasan"], "info": "", "contoh": []}]}]}