{"pranala": "https://kbbi.kemdikbud.go.id/entri/tal", "entri": [{"nama": "tal", "nomor": "1", "kata_dasar": [], "pelafalan": "", "bentuk_tidak_baku": [], "varian": [], "makna": [{"kelas": [{"kode": "n", "nama": "Nomina", "deskripsi": "kata benda"}], "submakna": ["tumbuhan palem, daunnya disebut rontal (kemudian menjadi lontar), digunakan untuk kertas tulis (zaman dulu dan sekarang masih digunakan di Bali)", "batang lontar"], "info": "\u3014Borassus fiabellifer\u3015", "contoh": []}, {"kelas": [{"kode": "n", "nama": "Nomina", "deskripsi": "kata benda"}], "submakna": ["daun tal"], "info": "", "contoh": []}]}, {"nama": "tal", "nomor": "2", "kata_dasar": [], "pelafalan": "", "bentuk_tidak_baku": [], "varian": [], "makna": [{"kelas": [{"kode": "n", "nama": "Nomina", "deskripsi": "kata benda"}, {"kode": "Lay", "nama": "Pelayaran", "deskripsi": "-"}], "submakna": ["tiang dayung yang terdapat pada sisi kiri dan sisi kanan buritan sampan tempat menyangkutkan gandar dayung pada kilas"], "info": "", "contoh": []}]}]}