{"pranala": "https://kbbi.kemdikbud.go.id/entri/tanda", "entri": [{"nama": "tan.da", "nomor": "", "kata_dasar": [], "pelafalan": "", "bentuk_tidak_baku": [], "varian": [], "makna": [{"kelas": [{"kode": "n", "nama": "Nomina", "deskripsi": "kata benda"}], "submakna": ["yang menjadi alamat atau yang menyatakan sesuatu"], "info": "", "contoh": ["dari kejauhan terdengar sirene -- bahaya"]}, {"kelas": [{"kode": "n", "nama": "Nomina", "deskripsi": "kata benda"}], "submakna": ["gejala"], "info": "", "contoh": ["sudah tampak --nya"]}, {"kelas": [{"kode": "n", "nama": "Nomina", "deskripsi": "kata benda"}], "submakna": ["bukti"], "info": "", "contoh": ["itulah -- bahwa mereka tidak mau bekerja sama"]}, {"kelas": [{"kode": "n", "nama": "Nomina", "deskripsi": "kata benda"}], "submakna": ["pengenal", "lambang"], "info": "", "contoh": ["kontingen Indonesia mengenakan -- Garuda Pancasila"]}, {"kelas": [{"kode": "n", "nama": "Nomina", "deskripsi": "kata benda"}], "submakna": ["petunjuk"], "info": "", "contoh": []}]}]}