{"pranala": "https://kbbi.kemdikbud.go.id/entri/teraju", "entri": [{"nama": "te.ra.ju", "nomor": "", "kata_dasar": [], "pelafalan": "/t\u00earaju/", "bentuk_tidak_baku": [], "varian": [], "makna": [{"kelas": [{"kode": "n", "nama": "Nomina", "deskripsi": "kata benda"}], "submakna": ["timbangan yang menggunakan dua buah piringan yang digantungkan dengan rantai (tali) pada kedua ujung lengannya", "neraca"], "info": "", "contoh": []}, {"kelas": [{"kode": "n", "nama": "Nomina", "deskripsi": "kata benda"}], "submakna": ["tali perentang kemah"], "info": "", "contoh": []}, {"kelas": [{"kode": "n", "nama": "Nomina", "deskripsi": "kata benda"}], "submakna": ["tali (rantai) untuk menggantungkan lampu dan sebagainya"], "info": "", "contoh": []}, {"kelas": [{"kode": "n", "nama": "Nomina", "deskripsi": "kata benda"}], "submakna": ["benang pada layang-layang yang diikatkan di sebelah atas dan bawahnya"], "info": "", "contoh": []}, {"kelas": [{"kode": "n", "nama": "Nomina", "deskripsi": "kata benda"}, {"kode": "ki", "nama": "kiasan", "deskripsi": ""}], "submakna": ["kekuasaan tertinggi", "pucuk pimpinan"], "info": "", "contoh": ["tampillah Tun Razak memegang -- Pemerintahan Malaysia"]}]}]}