{"pranala": "https://kbbi.kemdikbud.go.id/entri/tes%20interval%20fifa", "entri": [{"nama": "tes interval FIFA", "nomor": "", "kata_dasar": ["tes"], "pelafalan": "", "bentuk_tidak_baku": [], "varian": [], "makna": [{"kelas": [{"kode": "Olr", "nama": "Olahraga", "deskripsi": "-"}], "submakna": ["tes untuk mengevaluasi kemampuan seseorang berulang kali melakukan interval selama jangka waktu yang lama, salah satu bagian tes kebugaran FIFA untuk wasit dan asisten wasit"], "info": "", "contoh": []}]}]}