{"pranala": "https://kbbi.kemdikbud.go.id/entri/xilem", "entri": [{"nama": "xi.lem", "nomor": "", "kata_dasar": [], "pelafalan": "/sil\u00e9m/", "bentuk_tidak_baku": [], "varian": [], "makna": [{"kelas": [{"kode": "n", "nama": "Nomina", "deskripsi": "kata benda"}], "submakna": ["jaringan pembuluh kayu, khususnya tumbuhan tinggi, yang merupakan sel penyokong dan pengalir-alir ikatan vaskular"], "info": "", "contoh": []}, {"kelas": [{"kode": "n", "nama": "Nomina", "deskripsi": "kata benda"}], "submakna": ["jaringan pembuluh pada tumbuhan tinggi yang terdiri atas trakeid berlignin, unsur pembuluh dan serat yang menghantar air dan garam-garam mineral yang diserap oleh akar ke seluruh bagian, menopang tubuh secara mekanis"], "info": "", "contoh": []}]}]}