{"pranala": "https://kbbi.kemdikbud.go.id/entri/ulkus", "entri": [{"nama": "ul.kus", "nomor": "", "kata_dasar": [], "pelafalan": "", "bentuk_tidak_baku": [], "varian": [], "makna": [{"kelas": [{"kode": "n", "nama": "Nomina", "deskripsi": "kata benda"}], "submakna": ["luka pada permukaan selaput lendir, khususnya membran yang melapisi bagian perut atau saluran pencernaan lainnya"], "info": "", "contoh": []}, {"kelas": [{"kode": "n", "nama": "Nomina", "deskripsi": "kata benda"}], "submakna": ["luka bernanah pada kulit yang tidak sukar sembuh, mengakibatkan kerusakan jaringan"], "info": "", "contoh": []}]}]}