{"pranala": "https://kbbi.kemdikbud.go.id/entri/unik", "entri": [{"nama": "unik", "nomor": "", "kata_dasar": [], "pelafalan": "", "bentuk_tidak_baku": [], "varian": [], "makna": [{"kelas": [{"kode": "a", "nama": "Adjektiva", "deskripsi": "kata yang menjelaskan nomina atau pronomina"}], "submakna": ["tersendiri dalam bentuk atau jenisnya", "lain daripada yang lain", "tidak ada persamaan dengan yang lain", "khusus"], "info": "", "contoh": ["operasi pencangkokan yang cukup -- telah berhasil, yaitu sebuah jantung buatan dicangkokkan pada bayi yang menderita penyakit jantung"]}]}]}