{"pranala": "http://kbbi.kemdikbud.go.id/entri/okulasi", "entri": [{"nama": "oku.la.si", "nomor": "", "kata_dasar": [], "pelafalan": "", "bentuk_tidak_baku": [], "varian": [], "makna": [{"kelas": [{"kode": "n", "nama": "Nomina", "deskripsi": "kata benda"}, {"kode": "Tan", "nama": "Pertanian", "deskripsi": "-"}], "submakna": ["cara meningkatkan mutu tumbuhan dengan menempelkan sepotong kulit pohon yang bermata dari batang atas pada suatu irisan pada kulit pohon lain dari batang bawah sehingga tumbuh bersatu menjadi tanaman baru"], "info": "", "contoh": []}]}]}