{"pranala": "https://kbbi.kemdikbud.go.id/entri/oratorium", "entri": [{"nama": "ora.to.ri.um", "nomor": "", "kata_dasar": [], "pelafalan": "", "bentuk_tidak_baku": [], "varian": [], "makna": [{"kelas": [{"kode": "n", "nama": "Nomina", "deskripsi": "kata benda"}, {"kode": "Kat", "nama": "Agama Katolik", "deskripsi": "-"}], "submakna": ["tempat sembahyang atau tempat berdoa", "kapel"], "info": "", "contoh": []}, {"kelas": [{"kode": "n", "nama": "Nomina", "deskripsi": "kata benda"}, {"kode": "Mus", "nama": "Musik", "deskripsi": "-"}], "submakna": ["jenis karya musik yang besar (yang tumbuh dari suatu kebiasaan di tempat peribadatan di kota Roma pada akhir abad ke-16) dengan bersumberkan Alkitab untuk penciptaannya"], "info": "", "contoh": []}]}]}