{"pranala": "https://kbbi.kemdikbud.go.id/entri/lasat", "entri": [{"nama": "la.sat", "nomor": "", "kata_dasar": [], "pelafalan": "", "bentuk_tidak_baku": [], "varian": [], "makna": [{"kelas": [{"kode": "a", "nama": "Adjektiva", "deskripsi": "kata yang menjelaskan nomina atau pronomina"}, {"kode": "Mk", "nama": "Minangkabau", "deskripsi": "-"}], "submakna": ["payah (tentang penyakit)"], "info": "", "contoh": []}, {"kelas": [{"kode": "a", "nama": "Adjektiva", "deskripsi": "kata yang menjelaskan nomina atau pronomina"}, {"kode": "Mk", "nama": "Minangkabau", "deskripsi": "-"}], "submakna": ["makin menjadi-jadi (tentang tangis)"], "info": "", "contoh": []}]}]}