{"pranala": "https://kbbi.kemdikbud.go.id/entri/kaci", "entri": [{"nama": "ka.ci", "nomor": "1", "kata_dasar": [], "pelafalan": "", "bentuk_tidak_baku": [], "varian": [], "makna": [{"kelas": [{"kode": "n", "nama": "Nomina", "deskripsi": "kata benda"}], "submakna": ["kain putih", "mori"], "info": "", "contoh": []}]}, {"nama": "ka.ci", "nomor": "2", "kata_dasar": [], "pelafalan": "", "bentuk_tidak_baku": [], "varian": [], "makna": [{"kelas": [{"kode": "a", "nama": "Adjektiva", "deskripsi": "kata yang menjelaskan nomina atau pronomina"}, {"kode": "Jk", "nama": "Melayu Jakarta", "deskripsi": "-"}], "submakna": ["benar", "sungguh"], "info": "", "contoh": []}]}, {"nama": "ka.ci", "nomor": "3", "kata_dasar": [], "pelafalan": "", "bentuk_tidak_baku": [], "varian": [], "makna": [{"kelas": [{"kode": "n", "nama": "Nomina", "deskripsi": "kata benda"}], "submakna": ["ikan laut, berwarna putih dengan corak totol-totol cokelat di seluruh tubuh (termasuk kepala), mencapai ukuran panjang 100 cm, berat 6,3 kg, hidup di perairan tropis dengan kedalaman 1\u2013170 m, tersebar di perairan Laut Merah dan Afrika Timur sampai Jepang, bagian selatan sampai Kaledonia Baru"], "info": "\u3014Diagramma pictum\u3015", "contoh": []}, {"kelas": [{"kode": "n", "nama": "Nomina", "deskripsi": "kata benda"}], "submakna": ["ikan laut yang tebal bibirnya, ukuran mencapai panjang 83 cm, berat 6,9 kg, hidup di perairan tropis, tersebar di perairan Teluk Persia sampai Srilangka"], "info": "\u3014Plectorhyncus pictus\u3015", "contoh": []}]}]}