{"pranala": "http://kbbi.kemdikbud.go.id/entri/kasihan", "entri": [{"nama": "ka.sih.an", "nomor": "", "kata_dasar": ["kasih (1)"], "pelafalan": "", "bentuk_tidak_baku": [], "varian": [], "makna": [{"kelas": [{"kode": "n", "nama": "Nomina", "deskripsi": "kata benda"}], "submakna": ["rasa iba hati", "rasa belas kasih"], "info": "", "contoh": ["pengemis tua itu hidup dari ~ orang"]}, {"kelas": [{"kode": "p", "nama": "Partikel", "deskripsi": "kelas kata yang meliputi kata depan, kata sambung, kata seru, kata sandang, ucapan salam"}], "submakna": ["seruan menyatakan rasa belas (karena melihat dan sebagainya)"], "info": "", "contoh": ["~ benar anak ini", "aduh, ~ anak itu, tiba-tiba menjadi cacat seumur hidup"]}]}]}