{"pranala": "http://kbbi.kemdikbud.go.id/entri/kecubung", "entri": [{"nama": "ke.cu.bung", "nomor": "", "kata_dasar": [], "pelafalan": "/k\u00eacubung/", "bentuk_tidak_baku": [], "varian": [], "makna": [{"kelas": [{"kode": "n", "nama": "Nomina", "deskripsi": "kata benda"}], "submakna": ["perdu, cabang-cabangnya berkayu, bunganya berbentuk corong dan berwarna putih atau ungu, bijinya memabukkan"], "info": "\u3014Datura fastuosa\u3015", "contoh": []}, {"kelas": [{"kode": "n", "nama": "Nomina", "deskripsi": "kata benda"}], "submakna": ["warna ungu serupa dengan bunga kecubung"], "info": "", "contoh": []}, {"kelas": [{"kode": "n", "nama": "Nomina", "deskripsi": "kata benda"}, {"kode": "Geo", "nama": "Geografi dan Geologi", "deskripsi": "-"}], "submakna": ["batu kuarsa, warnanya bervariasi dari warna cerah sampai gelap, digunakan sebagai batu mulia"], "info": "\u3008SiO2\u3009", "contoh": []}]}]}