{"pranala": "https://kbbi.kemdikbud.go.id/entri/kepunahan%20massal", "entri": [{"nama": "kepunahan massal", "nomor": "", "kata_dasar": ["punah", "kepunahan"], "pelafalan": "", "bentuk_tidak_baku": [], "varian": [], "makna": [{"kelas": [{"kode": "Bio", "nama": "Biologi", "deskripsi": "-"}], "submakna": ["peristiwa menurunnya keanekaragaman dan keberlimpahan kehidupan makroskopis secara tajam, terjadi ketika laju kepunahan meningkat berbanding dengan laju spesiasi, misalnya peristiwa kepunahan Kapur-Tersier yang menandai kepunahan spesies dinosaurus"], "info": "", "contoh": []}]}]}