{"pranala": "http://kbbi.kemdikbud.go.id/entri/kesalingan", "entri": [{"nama": "ke.sa.ling.an", "nomor": "", "kata_dasar": ["saling (1)"], "pelafalan": "", "bentuk_tidak_baku": [], "varian": [], "makna": [{"kelas": [{"kode": "n", "nama": "Nomina", "deskripsi": "kata benda"}, {"kode": "Ling", "nama": "Linguistik", "deskripsi": "-"}], "submakna": ["bentuk bahasa yang menunjukkan makna timbal balik atau saling"], "info": "", "contoh": ["~ dapat diungkapkan secara leksikal, gramatikal, atau secara kedua-duanya"]}]}]}