{"pranala": "http://kbbi.kemdikbud.go.id/entri/konteks%20situasi", "entri": [{"nama": "konteks situasi", "nomor": "", "kata_dasar": ["konteks"], "pelafalan": "", "bentuk_tidak_baku": [], "varian": [], "makna": [{"kelas": [{"kode": "Ling", "nama": "Linguistik", "deskripsi": "-"}], "submakna": ["lingkungan nonlinguistis ujaran yang merupakan alat untuk memerinci ciri-ciri situasi yang diperlukan untuk memahami makna ujaran"], "info": "", "contoh": []}]}, {"nama": "konteks situasi", "nomor": "", "kata_dasar": ["konteks"], "pelafalan": "", "bentuk_tidak_baku": [], "varian": [], "makna": [{"kelas": [{"kode": "Sen", "nama": "Kesenian", "deskripsi": "-"}], "submakna": ["pertunjukan bertema kontekstual"], "info": "", "contoh": []}]}]}