{"pranala": "http://kbbi.kemdikbud.go.id/entri/dakocan%20putih", "entri": [{"nama": "dakocan putih", "nomor": "", "kata_dasar": ["dakocan"], "pelafalan": "", "bentuk_tidak_baku": [], "varian": [], "makna": [{"kelas": [], "submakna": ["ikan laut, tubuh berbentuk lebar berwarna putih, sirip berwarna hitam kecuali sirip ekor berwarna putih, terdapat garis hitam di pangkal sirip ventral sampai pangkal sirip dorsal, panjang mencapai 7 cm, hidup di terumbu karang perairan tropis dengan kedalaman 5\u201340 m"], "info": "\u3014Dascyllus carneus\u3015", "contoh": []}]}]}