{"pranala": "https://kbbi.kemdikbud.go.id/entri/gravitasi", "entri": [{"nama": "gra.vi.ta.si", "nomor": "", "kata_dasar": [], "pelafalan": "", "bentuk_tidak_baku": ["grafitasi"], "varian": [], "makna": [{"kelas": [{"kode": "n", "nama": "Nomina", "deskripsi": "kata benda"}, {"kode": "Geo", "nama": "Geografi dan Geologi", "deskripsi": "-"}], "submakna": ["kekuatan (gaya) tarik bumi"], "info": "", "contoh": []}, {"kelas": [{"kode": "n", "nama": "Nomina", "deskripsi": "kata benda"}, {"kode": "Geo", "nama": "Geografi dan Geologi", "deskripsi": "-"}], "submakna": ["proses gaya tarik bumi"], "info": "", "contoh": []}, {"kelas": [{"kode": "n", "nama": "Nomina", "deskripsi": "kata benda"}, {"kode": "Geo", "nama": "Geografi dan Geologi", "deskripsi": "-"}], "submakna": ["gaya berat suatu benda"], "info": "", "contoh": []}]}]}