{"pranala": "https://kbbi.kemdikbud.go.id/entri/rela", "entri": [{"nama": "re.la", "nomor": "", "kata_dasar": [], "pelafalan": "/r\u00e8la/", "bentuk_tidak_baku": ["reda"], "varian": [], "makna": [{"kelas": [{"kode": "v", "nama": "Verba", "deskripsi": "kata kerja"}], "submakna": ["bersedia dengan ikhlas hati"], "info": "", "contoh": ["aku -- mati membela tanah tumpah darahku"]}, {"kelas": [{"kode": "v", "nama": "Verba", "deskripsi": "kata kerja"}], "submakna": ["izin (persetujuan)", "perkenan"], "info": "", "contoh": ["kedatangan saya ini hendak meminta -- tuan"]}, {"kelas": [{"kode": "v", "nama": "Verba", "deskripsi": "kata kerja"}], "submakna": ["dapat diterima dengan senang hati"], "info": "", "contoh": ["semua itu kuberikan kepadamu dengan --"]}, {"kelas": [{"kode": "v", "nama": "Verba", "deskripsi": "kata kerja"}], "submakna": ["tidak mengharap imbalan, dengan kehendak atau kemauan sendiri"], "info": "", "contoh": ["dengan suka --"]}]}]}